label_studio_withoutsignin/__init__.py
label_studio_withoutsignin/manage.py
label_studio_withoutsignin/pytest.ini
label_studio_withoutsignin/server.py
label_studio_withoutsignin/sitecustomize.py
label_studio_withoutsignin/annotation_templates/CONTRIBUTING.md
label_studio_withoutsignin/annotation_templates/README.md
label_studio_withoutsignin/annotation_templates/groups.txt
label_studio_withoutsignin/annotation_templates/audio-speech-processing/automatic-speech-recognition/config.xml
label_studio_withoutsignin/annotation_templates/audio-speech-processing/automatic-speech-recognition/config.yml
label_studio_withoutsignin/annotation_templates/audio-speech-processing/automatic-speech-recognition-using-segments/config.xml
label_studio_withoutsignin/annotation_templates/audio-speech-processing/automatic-speech-recognition-using-segments/config.yml
label_studio_withoutsignin/annotation_templates/audio-speech-processing/intent-classification/config.xml
label_studio_withoutsignin/annotation_templates/audio-speech-processing/intent-classification/config.yml
label_studio_withoutsignin/annotation_templates/audio-speech-processing/signal-quality-detection/config.xml
label_studio_withoutsignin/annotation_templates/audio-speech-processing/signal-quality-detection/config.yml
label_studio_withoutsignin/annotation_templates/audio-speech-processing/sound-event-detection/config.xml
label_studio_withoutsignin/annotation_templates/audio-speech-processing/sound-event-detection/config.yml
label_studio_withoutsignin/annotation_templates/audio-speech-processing/speaker-segmentation/config.xml
label_studio_withoutsignin/annotation_templates/audio-speech-processing/speaker-segmentation/config.yml
label_studio_withoutsignin/annotation_templates/computer-vision/image-captioning/config.yml
label_studio_withoutsignin/annotation_templates/computer-vision/image-classification/config.yml
label_studio_withoutsignin/annotation_templates/computer-vision/object-detection-with-bounding-boxes/config.yml
label_studio_withoutsignin-1.0.12.dist-info/LICENSE
label_studio_withoutsignin-1.0.12.dist-info/METADATA
label_studio_withoutsignin-1.0.12.dist-info/NOTICE
label_studio_withoutsignin-1.0.12.dist-info/WHEEL
label_studio_withoutsignin-1.0.12.dist-info/entry_points.txt
label_studio_withoutsignin-1.0.12.dist-info/top_level.txt
label_studio_withoutsignin-1.0.12.dist-info/RECORD
