Metadata-Version: 2.1
Name: label-studio-withoutsignin
Version: 1.0.12
Summary: Label Studio without sign in user access
Home-page: https://github.com/DimaVinnitsa/label-studio
Author: dmytro.bershov
Author-email: 
License: UNKNOWN
Platform: UNKNOWN
Classifier: Programming Language :: Python :: 3
Classifier: License :: OSI Approved :: Apache Software License
Classifier: Operating System :: OS Independent
Requires-Python: >=3.6
Requires-Dist: wheel
Requires-Dist: appdirs (>=1.4.3)
Requires-Dist: attr (==0.3.1)
Requires-Dist: attrs (>=19.2.0)
Requires-Dist: pyyaml (>=5.3.1)
Requires-Dist: azure-storage-blob (>=12.6.0)
Requires-Dist: boto (==2.49.0)
Requires-Dist: boto3 (==1.16.28)
Requires-Dist: botocore (==1.19.28)
Requires-Dist: google-cloud-storage (==1.28.1)
Requires-Dist: Django (==3.1.4)
Requires-Dist: django-annoying (==0.10.6)
Requires-Dist: django-debug-toolbar (==3.2)
Requires-Dist: django-filter (==2.4.0)
Requires-Dist: django-model-utils (==4.1.1)
Requires-Dist: django-rq (==2.3.2)
Requires-Dist: django-cors-headers (==3.6.0)
Requires-Dist: django-extensions (==3.1.0)
Requires-Dist: django-rest-swagger (==2.2.0)
Requires-Dist: django-user-agents (==0.4.0)
Requires-Dist: django-ranged-fileresponse (==0.1.2)
Requires-Dist: django-redis-cache (==3.0.0)
Requires-Dist: drf-dynamic-fields (==0.3.0)
Requires-Dist: drf-yasg (==1.20.0)
Requires-Dist: drf-generators (==0.3.0)
Requires-Dist: label-studio-converter (==0.0.28)
Requires-Dist: htmlmin (==0.1.12)
Requires-Dist: jsonschema (==3.2.0)
Requires-Dist: lockfile (>=0.12.0)
Requires-Dist: lxml (>=4.2.5)
Requires-Dist: moto (==1.3.16.dev122)
Requires-Dist: numpy (>=1.19.1)
Requires-Dist: ordered-set (==4.0.2)
Requires-Dist: pandas (>=0.24.0)
Requires-Dist: protobuf (>=3.15.5)
Requires-Dist: psycopg2-binary (==2.8.4)
Requires-Dist: pydantic (==1.7.3)
Requires-Dist: python-dateutil (==2.8.1)
Requires-Dist: pytz (==2019.3)
Requires-Dist: requests (<3,>=2.22.0)
Requires-Dist: rq (==1.7.0)
Requires-Dist: rules (==2.2)
Requires-Dist: ujson (>=3.0.0)
Requires-Dist: xmljson (==0.2.0)
Requires-Dist: colorama (>=0.4.4)
Requires-Dist: boxing (>=0.1.4)
Requires-Dist: redis (>=3.5.0)
